{"appleSKU":"","appleTeamID":"","enableCodelessAutoInitialization":true,"enableUnityGamingServicesAutoInitialization":true,"products":[{"id":"com.adadi.rightclick.3hearts","type":0,"storeIDs":[],"defaultDescription":{"googleLocale":21,"title":"3 hearts","description":"On game over, allowing get back to the game with 3 hearts"},"screenshotPath":"","applePriceTier":1,"googlePrice":{"data":[99,0,0,131072],"num":0.99},"pricingTemplateID":"","descriptions":[],"payouts":[]},{"id":"com.adadi.rightclick.8hearts_new","type":0,"storeIDs":[],"defaultDescription":{"googleLocale":21,"title":"8 hearts","description":"On game over, allowing get back to the game with 8 hearts"},"screenshotPath":"","applePriceTier":2,"googlePrice":{"data":[199,0,0,131072],"num":1.99},"pricingTemplateID":"","descriptions":[],"payouts":[]},{"id":"com.adadi.rightclick.plus2hearts_every_game_regular_new","type":1,"storeIDs":[],"defaultDescription":{"googleLocale":21,"title":"+2 hearts every game","description":"Get +2 hearts at the begining of each game. Regular price"},"screenshotPath":"","applePriceTier":3,"googlePrice":{"data":[299,0,0,131072],"num":2.99},"pricingTemplateID":"","descriptions":[],"payouts":[]},{"id":"com.adadi.rightclick.plus2hearts_every_game_premium_new","type":1,"storeIDs":[],"defaultDescription":{"googleLocale":21,"title":"+2 hearts every game Premiumr","description":"+2 hearts every game. Premium price - need to pass a challenge to enable it."},"screenshotPath":"","applePriceTier":1,"googlePrice":{"data":[99,0,0,131072],"num":0.99},"pricingTemplateID":"","descriptions":[],"payouts":[]},{"id":"com.adadi.rightclick.3hearts_new","type":0,"storeIDs":[],"defaultDescription":{"googleLocale":21,"title":"3 hearts","description":"On game over, allowing get back to the game with 3 hearts"},"screenshotPath":"","applePriceTier":0,"googlePrice":{"data":[5,0,0,65536],"num":0.5},"pricingTemplateID":"","descriptions":[],"payouts":[]}]}